munch/__init__.py
munch/python3_compat.py
munch-3.0.0.dist-info/AUTHORS
munch-3.0.0.dist-info/LICENSE.txt
munch-3.0.0.dist-info/METADATA
munch-3.0.0.dist-info/WHEEL
munch-3.0.0.dist-info/pbr.json
munch-3.0.0.dist-info/top_level.txt
munch-3.0.0.dist-info/RECORD
