Metadata-Version: 2.1
Name: munch
Version: 3.0.0
Summary: A dot-accessible dictionary (a la JavaScript objects)
Home-page: https://github.com/Infinidat/munch
Author: Rotem Yaari
Author-email: vmalloc@gmail.com
License: MIT
Keywords: munch,dict,mapping,container,collection
Classifier: Development Status :: 5 - Production/Stable
Classifier: Intended Audience :: Developers
Classifier: Operating System :: OS Independent
Classifier: Programming Language :: Python
Classifier: Programming Language :: Python :: 3.6
Classifier: Programming Language :: Python :: 3.7
Classifier: Programming Language :: Python :: 3.8
Classifier: Programming Language :: Python :: 3.9
Classifier: Programming Language :: Python :: 3.10
Classifier: Programming Language :: Python :: 3.11
Classifier: Topic :: Software Development
Classifier: Topic :: Software Development :: Libraries
Classifier: Topic :: Utilities
Classifier: License :: OSI Approved :: MIT License
Requires-Python: >=3.6
Provides-Extra: testing
Provides-Extra: yaml
License-File: LICENSE.txt
